WeiruanGuanfangCZhinan20171224/README.md
WeiruanGuanfangCZhinan20171224/__init__.py
WeiruanGuanfangCZhinan20171224/__main__.py
WeiruanGuanfangCZhinan20171224/file.epub
WeiruanGuanfangCZhinan20171224/index.html
WeiruanGuanfangCZhinan20171224/css/__init__.py
WeiruanGuanfangCZhinan20171224/css/annotations.css
WeiruanGuanfangCZhinan20171224/css/main.css
WeiruanGuanfangCZhinan20171224/css/normalize.css
WeiruanGuanfangCZhinan20171224/css/popup.css
WeiruanGuanfangCZhinan20171224/font/__init__.py
WeiruanGuanfangCZhinan20171224/font/fontello.eot
WeiruanGuanfangCZhinan20171224/font/fontello.svg
WeiruanGuanfangCZhinan20171224/font/fontello.ttf
WeiruanGuanfangCZhinan20171224/font/fontello.woff
WeiruanGuanfangCZhinan20171224/img/__init__.py
WeiruanGuanfangCZhinan20171224/img/annotator-glyph-sprite.png
WeiruanGuanfangCZhinan20171224/img/annotator-icon-sprite.png
WeiruanGuanfangCZhinan20171224/img/apple-touch-icon.png
WeiruanGuanfangCZhinan20171224/img/cancelfullscreen.png
WeiruanGuanfangCZhinan20171224/img/close.png
WeiruanGuanfangCZhinan20171224/img/fullscreen.png
WeiruanGuanfangCZhinan20171224/img/loader.gif
WeiruanGuanfangCZhinan20171224/img/menu-icon.png
WeiruanGuanfangCZhinan20171224/img/save.png
WeiruanGuanfangCZhinan20171224/img/saved.png
WeiruanGuanfangCZhinan20171224/img/settings-s.png
WeiruanGuanfangCZhinan20171224/img/settings.png
WeiruanGuanfangCZhinan20171224/img/star.png
WeiruanGuanfangCZhinan20171224/js/__init__.py
WeiruanGuanfangCZhinan20171224/js/epub.js
WeiruanGuanfangCZhinan20171224/js/epub.min.js
WeiruanGuanfangCZhinan20171224/js/epub.min.map
WeiruanGuanfangCZhinan20171224/js/hooks.min.js
WeiruanGuanfangCZhinan20171224/js/hooks.min.map
WeiruanGuanfangCZhinan20171224/js/reader.js
WeiruanGuanfangCZhinan20171224/js/reader.js.map
WeiruanGuanfangCZhinan20171224/js/reader.min.js
WeiruanGuanfangCZhinan20171224/js/reader.min.map
WeiruanGuanfangCZhinan20171224/js/hooks/__init__.py
WeiruanGuanfangCZhinan20171224/js/hooks/extensions/__init__.py
weiruan_guanfang_c_zhinan_20171224-2024.3.2.0.dist-info/METADATA
weiruan_guanfang_c_zhinan_20171224-2024.3.2.0.dist-info/WHEEL
weiruan_guanfang_c_zhinan_20171224-2024.3.2.0.dist-info/entry_points.txt
weiruan_guanfang_c_zhinan_20171224-2024.3.2.0.dist-info/top_level.txt
weiruan_guanfang_c_zhinan_20171224-2024.3.2.0.dist-info/RECORD
